binance_sdk_derivatives_trading_usds_futures/__init__.py
binance_sdk_derivatives_trading_usds_futures/derivatives_trading_usds_futures.py
binance_sdk_derivatives_trading_usds_futures/metadata.py
binance_sdk_derivatives_trading_usds_futures/rest_api/__init__.py
binance_sdk_derivatives_trading_usds_futures/rest_api/api/__init__.py
binance_sdk_derivatives_trading_usds_futures/rest_api/api/account_api.py
binance_sdk_derivatives_trading_usds_futures/rest_api/api/convert_api.py
binance_sdk_derivatives_trading_usds_futures/rest_api/api/market_data_api.py
binance_sdk_derivatives_trading_usds_futures/rest_api/api/portfolio_margin_endpoints_api.py
binance_sdk_derivatives_trading_usds_futures/rest_api/api/trade_api.py
binance_sdk_derivatives_trading_usds_futures/rest_api/api/user_data_streams_api.py
binance_sdk_derivatives_trading_usds_futures/rest_api/models/__init__.py
binance_sdk_derivatives_trading_usds_futures/rest_api/models/accept_the_offered_quote_response.py
binance_sdk_derivatives_trading_usds_futures/rest_api/models/account_information_v2_response.py
binance_sdk_derivatives_trading_usds_futures/rest_api/models/account_information_v2_response_assets_inner.py
binance_sdk_derivatives_trading_usds_futures/rest_api/models/account_information_v2_response_positions_inner.py
binance_sdk_derivatives_trading_usds_futures/rest_api/models/account_information_v3_response.py
binance_sdk_derivatives_trading_usds_futures/rest_api/models/account_information_v3_response_assets_inner.py
binance_sdk_derivatives_trading_usds_futures/rest_api/models/account_information_v3_response_positions_inner.py
binance_sdk_derivatives_trading_usds_futures/rest_api/models/account_trade_list_response.py
binance_sdk_derivatives_trading_usds_futures/rest_api/models/account_trade_list_response_inner.py
binance_sdk_derivatives_trading_usds_futures/rest_api/models/adl_risk_response.py
binance_sdk_derivatives_trading_usds_futures/rest_api/models/adl_risk_response1.py
binance_sdk_derivatives_trading_usds_futures-6.0.0.dist-info/METADATA
binance_sdk_derivatives_trading_usds_futures-6.0.0.dist-info/WHEEL
binance_sdk_derivatives_trading_usds_futures-6.0.0.dist-info/licenses/LICENCE
binance_sdk_derivatives_trading_usds_futures-6.0.0.dist-info/RECORD
